examples/__init__.py
examples/simple_measurement.py
pyxperiment/__init__.py
pyxperiment/__main__.py
pyxperiment/controller/__init__.py
pyxperiment/controller/control_manager.py
pyxperiment/controller/data_context.py
pyxperiment/controller/data_provider.py
pyxperiment/controller/data_storage.py
pyxperiment/controller/device_control.py
pyxperiment/controller/device_factory.py
pyxperiment/controller/device_options.py
pyxperiment/controller/instrument.py
pyxperiment/controller/instrument_module.py
pyxperiment/controller/tcp_instrument.py
pyxperiment/controller/time_device.py
pyxperiment/controller/validation.py
pyxperiment/controller/visa_instrument.py
pyxperiment/controller/zurich_instrument.py
pyxperiment/core/__init__.py
pyxperiment/core/application.py
pyxperiment/core/experiment.py
pyxperiment/core/utils.py
pyxperiment/data_format/__init__.py
pyxperiment/data_format/columned_data_format.py
pyxperiment/data_format/text_data_format.py
pyxperiment/data_storage/__init__.py
pyxperiment/data_storage/data_access.py
pyxperiment/data_storage/data_provider.py
pyxperiment/data_storage/data_storage.py
pyxperiment/devices/__init__.py
pyxperiment/devices/ami430.py
pyxperiment/devices/attocubeANC300.py
pyxperiment/devices/avs47.py
pyxperiment/devices/smxxxx.py
pyxperiment/devices/sr5113.py
pyxperiment/devices/sr72x5.py
pyxperiment/devices/tektronix4323.py
pyxperiment/devices/tektronixAFG3xxx.py
pyxperiment/devices/testdevice.py
pyxperiment/devices/agilent/__init__.py
pyxperiment/devices/agilent/agilent_344xx.py
pyxperiment/devices/agilent/agilent_b1500a.py
pyxperiment/devices/agilent/agilent_b29xxx.py
pyxperiment/devices/agilent/agilent_dsox12xx.py
pyxperiment/devices/agilent/agilent_e444xa.py
pyxperiment/devices/agilent/agilent_e8257.py
pyxperiment/devices/agilent/agilent_n9000a.py
pyxperiment/devices/keithley/__init__.py
pyxperiment/devices/keithley/keithley_2182.py
pyxperiment/devices/keithley/keithley_2400.py
pyxperiment/devices/keithley/keithley_2700.py
pyxperiment-0.1.3.dist-info/LICENSE
pyxperiment-0.1.3.dist-info/METADATA
pyxperiment-0.1.3.dist-info/WHEEL
pyxperiment-0.1.3.dist-info/top_level.txt
pyxperiment-0.1.3.dist-info/RECORD
